CHANGELOG.md
LICENSE
MANIFEST.in
README.md
setup.cfg
setup.py
pip_services_net/__init__.py
pip_services_net.egg-info/PKG-INFO
pip_services_net.egg-info/SOURCES.txt
pip_services_net.egg-info/dependency_links.txt
pip_services_net.egg-info/requires.txt
pip_services_net.egg-info/top_level.txt
pip_services_net.egg-info/zip-safe
pip_services_net/direct/DirectClient.py
pip_services_net/direct/__init__.py
pip_services_net/messaging/IMessageQueue.py
pip_services_net/messaging/IMessageReceiver.py
pip_services_net/messaging/MemoryMessageQueue.py
pip_services_net/messaging/MessageEnvelop.py
pip_services_net/messaging/MessageQueue.py
pip_services_net/messaging/MessagingCapabilities.py
pip_services_net/messaging/__init__.py
pip_services_net/rest/CommandableHttpClient.py
pip_services_net/rest/CommandableHttpService.py
pip_services_net/rest/RestClient.py
pip_services_net/rest/RestQueryParams.py
pip_services_net/rest/RestService.py
pip_services_net/rest/SimpleServer.py
pip_services_net/rest/__init__.py
test/Dummy.py
test/DummyClientFixture.py
test/DummyController.py
test/__init__.py
test/direct/DummyDirectClient.py
test/direct/__init__.py
test/direct/test_DummyDirectClient.py
test/messaging/MessageQueueFixture.py
test/messaging/__init__.py
test/messaging/test_MemoryMessageQueue.py
test/rest/DummyCommandableHttpClient.py
test/rest/DummyCommandableHttpService.py
test/rest/DummyRestClient.py
test/rest/DummyRestService.py
test/rest/__init__.py
test/rest/test_DummyCommandableHttpClient.py
test/rest/test_DummyRestClient.py